<FridgeWidget xmlns="runtime-namespace:Game">
  <BevelledRectangleWidget Size="614, 382" BevelSize="3" />
  
  <GridPanelWidget Name="InventoryGrid" CanvasWidget.Position="306, 52" ColumnsCount="4" RowsCount="4"/>
  <GridPanelWidget Name="FlameFurnaceGrid" CanvasWidget.Position="12, 45" ColumnsCount="4" RowsCount="4" />
  <CanvasWidget CanvasWidget.Position="90, 210" >
    <FireWidget Name="Fire" Size="104, 40" HorizontalAlignment="Center" VerticalAlignment="Center"/>
    <StackPanelWidget Direction="Horizontal">
      <BevelledRectangleWidget Size="24, 44" BevelSize="-2" CenterColor="0, 0, 0, 0" />
      <BevelledRectangleWidget Size="24, 44" BevelSize="-2" CenterColor="0, 0, 0, 0" />
      <BevelledRectangleWidget Size="24, 44" BevelSize="-2" CenterColor="0, 0, 0, 0" />
      <BevelledRectangleWidget Size="24, 44" BevelSize="-2" CenterColor="0, 0, 0, 0" />
      <BevelledRectangleWidget Size="24, 44" BevelSize="-2" CenterColor="0, 0, 0, 0" />      
    </StackPanelWidget>
	
  </CanvasWidget>  
  
  <CanvasWidget CanvasWidget.Position="190, 50" Size = "100,150" >
	  <BevelledRectangleWidget Size="190, 250" BevelSize="-4" />
	    <CanvasWidget CanvasWidget.Position="10, 10" Size = "80,130" >
		    <ScrollPanelWidget Direction="Vertical" >
		  
				<LabelWidget FontScale = "0.5" Text="炼制台往往下俩排放材料，上两排放水瓶之类的前置物品。合成表可以在右上角的万象设置查看" WordWrap="true" Color="255, 255, 255, 255" HorizontalAlignment="Center" VerticalAlignment="Center"/>
			  
		    </ScrollPanelWidget>
		</CanvasWidget>
  </CanvasWidget> 
  <ValueBarWidget Name="Progress" CanvasWidget.Position="100, 260" LayoutDirection="Horizontal" BarsCount="8" FlipDirection="false" LitBarColor="96, 48, 0" UnlitBarColor="48, 48, 48, 80" BarSize="12, 12" BarSubtexture="{Textures/Atlas/ProgressBar}"/>
  <InventorySlotWidget Name="FuelSlot" CanvasWidget.Position="60, 288">
    <LabelWidget Text="燃料"  Color="0, 0, 0, 64" HorizontalAlignment="Center" VerticalAlignment="Center"/>
  </InventorySlotWidget>
  <InventorySlotWidget Name="ResultSlot" CanvasWidget.Position="220, 288" >
    <LabelWidget Text="产品"  Color="0, 0, 0, 64" HorizontalAlignment="Center" VerticalAlignment="Center"/>
  </InventorySlotWidget>  
  <InventorySlotWidget Name="RemainsSlot" CanvasWidget.Position="220, 208">
    <LabelWidget Text="副产品"  Color="0, 0, 0, 64" HorizontalAlignment="Center" VerticalAlignment="Center"/>
  </InventorySlotWidget>  
  <LabelWidget CanvasWidget.Position="12, 14" Text="炼制台"  Color="255, 255, 255, 192"/>
  <LabelWidget CanvasWidget.Position="306, 14" Text="背包"  Color="255, 255, 255, 192"/>  
  <ArrowLineWidget Color="0, 0, 0, 96" Width="8" ArrowWidth="0" PointsString="30, 210; 30, 324; 50, 324" AbsoluteCoordinates="true"/>
  <ArrowLineWidget Color="0, 0, 0, 96" Width="8" ArrowWidth="24" PointsString="150, 324; 196, 324" AbsoluteCoordinates="true"/>
  
</FridgeWidget>

